welearn_database/__init__.py
welearn_database/alembic/README
welearn_database/alembic/env.py
welearn_database/alembic/script.py.mako
welearn_database/alembic/versions/068312e7800c_add_referrer_origin_column_to_user_and_.py
welearn_database/alembic/versions/0e0bc0fca384_doc_qty_per_source.py
welearn_database/alembic/versions/16ff997426d3_remove_error_retrieval_unique_constraint.py
welearn_database/alembic/versions/2ad4895b2674_data_collection.py
welearn_database/alembic/versions/4c7161819e5a_grafana_views.py
welearn_database/alembic/versions/4f5a188dd614_add_main_url_column.py
welearn_database/alembic/versions/4fcbfb7f3145_added_api_key_management_table.py
welearn_database/alembic/versions/5d82613c9aca_context_document.py
welearn_database/alembic/versions/821173cf9c5d_initial_migration.py
welearn_database/alembic/versions/84c42739c17b_create_table_errordataquality.py
welearn_database/alembic/versions/89920abb7ff8_add_category.py
welearn_database/alembic/versions/96bba9e4842a_merge_external_id_error_quality.py
welearn_database/alembic/versions/a50a1db3ca2a_add_used_since_column_for_embeddings.py
welearn_database/alembic/versions/b031206324b7_agent_related.py
welearn_database/alembic/versions/ccdbd708c997_create_column_external_id.py
welearn_database/alembic/versions/e354666f951d_inferred_user.py
welearn_database/data/__init__.py
welearn_database/data/enumeration.py
welearn_database/data/models/__init__.py
welearn_database/data/models/agent_related.py
welearn_database/data/models/corpus_related.py
welearn_database/data/models/document_related.py
welearn_database/data/models/grafana.py
welearn_database/data/models/user_related.py
welearn_database/database_utils.py
welearn_database/exceptions.py
welearn_database/modules/__init__.py
welearn_database/modules/text_cleaning.py
welearn_database-1.3.0.dist-info/LICENSE
welearn_database-1.3.0.dist-info/METADATA
welearn_database-1.3.0.dist-info/WHEEL
welearn_database-1.3.0.dist-info/RECORD
