Metadata-Version: 2.3
Name: welearn-database
Version: 1.3.0
Summary: All stuff related to relationnal database from the WeLearn project
License: cc-by-sa-nc
Author: Théo
Author-email: theo.nardin@cri-paris.org
Requires-Python: >=3.10
Classifier: License :: Other/Proprietary License
Classifier: Programming Language :: Python :: 3
Classifier: Programming Language :: Python :: 3.10
Classifier: Programming Language :: Python :: 3.11
Classifier: Programming Language :: Python :: 3.12
Classifier: Programming Language :: Python :: 3.13
Requires-Dist: alembic (>=1.16.5,<2.0.0)
Requires-Dist: psycopg2-binary (>=2.9.11,<3.0.0)
Requires-Dist: python-dotenv (>=1.1.1,<2.0.0)
Requires-Dist: sqlalchemy (>=2.0.43,<3.0.0)
